reliability_stability/__init__.py
reliability_stability/reliability_stability.py
reliability_stability_pkg/__init__.py
reliability_stability_pkg/reliability_stability.py
reliability_stability_calc-0.0.4.dist-info/METADATA
reliability_stability_calc-0.0.4.dist-info/WHEEL
reliability_stability_calc-0.0.4.dist-info/entry_points.txt
reliability_stability_calc-0.0.4.dist-info/top_level.txt
reliability_stability_calc-0.0.4.dist-info/RECORD
