Metadata-Version: 2.1
Name: reliability-stability-calc
Version: 0.0.4
Summary: Calculation for relibability and stability three data sets
Home-page: https://github.com/nimh-mbdu/data-reliability-stability
Author: Lily Eisner
Author-email: lillian.eisner@gmail.com
License: UNKNOWN
Platform: UNKNOWN
Classifier: Programming Language :: Python :: 3
Classifier: License :: CC0 1.0 Universal (CC0 1.0) Public Domain Dedication
Classifier: Operating System :: POSIX
Requires-Dist: pandas
Requires-Dist: numpy
Requires-Dist: nibabel
Requires-Dist: Click
